ilc/__init__.py
ilc/control_handler.py
ilc/criteria_handler.py
ilc/ilc_agent.py
ilc/ilc_matrices.py
ilc/utils.py
volttron_ilc-2.2.2.dist-info/LICENSE
volttron_ilc-2.2.2.dist-info/METADATA
volttron_ilc-2.2.2.dist-info/WHEEL
volttron_ilc-2.2.2.dist-info/entry_points.txt
volttron_ilc-2.2.2.dist-info/RECORD
