Metadata-Version: 2.1
Name: volttron-ilc
Version: 2.2.2
Summary: ILC supports traditional demand response as well as transactive energy services. ILC manages controllable loads while also mitigating service-level excursions (e.g., occupant comfort, minimizing equipment ON/OFF cycling) by dynamically prioritizing available loads for curtailment using both quantitative (deviation of zone conditions from set point) and qualitative rules (type of zone).IXME
Home-page: https://github.com/eclipse-volttron/volttron-ilc
License: Apache-2.0
Author: Robert Lutes
Author-email: robert.lutes@pnnl.gov
Requires-Python: >=3.10,<4.0
Classifier: Intended Audience :: Developers
Classifier: Intended Audience :: Information Technology
Classifier: Intended Audience :: Other Audience
Classifier: Intended Audience :: Science/Research
Classifier: License :: OSI Approved :: Apache Software License
Classifier: Programming Language :: Python :: 3
Classifier: Programming Language :: Python :: 3.10
Classifier: Programming Language :: Python :: 3.11
Classifier: Programming Language :: Python :: 3.12
Classifier: Programming Language :: Python :: 3 :: Only
Requires-Dist: sympy (>=1.12,<2.0)
Requires-Dist: transitions (>=0.9.0,<0.10.0)
Requires-Dist: volttron (>=10.0.5rc0,<11.0)
Project-URL: Repository, https://github.com/eclipse-volttron/volttron-ilc
